LICENSE
README.md
setup.cfg
setup.py
chrome_driver_exe_update/__init__.py
chrome_driver_exe_update/chrome_driver.py
chrome_driver_exe_update/cli.py
chrome_driver_exe_update.egg-info/PKG-INFO
chrome_driver_exe_update.egg-info/SOURCES.txt
chrome_driver_exe_update.egg-info/dependency_links.txt
chrome_driver_exe_update.egg-info/entry_points.txt
chrome_driver_exe_update.egg-info/requires.txt
chrome_driver_exe_update.egg-info/top_level.txt
tests/__init__.py
tests/test_chrome_driver.py